{
  "name": "Rift Runners TCG",
  "menuBackgroundImage": "https://cdn.shopify.com/s/files/1/0633/2284/9480/files/rift-runner-game-logo-rev1.png",
  "defaultRessources": {
    "backgrounds": [],
    "decksUrl": ""
  },
  "customHelp": "",
  "cardRotation": "90",
  "cards": {
    "dataUrl": "https://balbi.github.io/TCGA-Rift-Runners/RiftRunnersTCG_Cards.json",
    "cardBack": "https://balbi.github.io/TCGA-Rift-Runners/backs/default.jpg"
  },
  "deckBuilding": {
    "mainFilters": [
      "type",
      "name",
      "Tier",
      "Element",
      "ATK",
      "DEF",
      "Unity ATK",
      "Unity DEF",
      "Set"
    ],
    "formats": [
      {
        "title": "Standard",
        "gameplay": "Standard",
        "deckRuleset": "Standard",
        "customCategories": [
          "Monarch",
          "Fodder"
        ]
      }
    ],
    "deckRulesets": {
      "Standard": {
        "reversedLegality": true,
        "general": {
          "maxPerCard": 3
        },
        "categories": [
          {
            "category": "Monarch",
            "min": 1,
            "max": 1
          },
          {
            "category": "Fodder",
            "min": 9,
            "max": 15
          }
        ]
      }
    }
  },
  "gameplay": {
    "Standard": {
      "mulligan": {
        "info": "",
        "startingHandSize": "5",
        "drawNewHand": false,
        "putSelectionAtBottom": false,
        "drawNewSelectedCards": false
      },
      "newTurn": {
        "drawOnStart": false,
        "sharedTurn": false,
        "firstPlayerTokenName": "",
        "drawPerTurn": 1
      },
      "defaultNotes": "",
      "tokens": [],
      "countersStartingValues": [
        "100"
      ],
      "hideFacedDownCards": false,
      "sections": {
        "customSections": [],
        "layout": {
          "direction": "row",
          "isSymetricalForOpponents": true,
          "content": [
            {
              "direction": "column",
              "style": {"width": "12vh", "justifyContent": "end"},
              "content": [
                {
                  "section": "Monarch",
                  "style": false
                },
                {
                  "section": "Fodder",
                  "style": false
                }
              ],
              "isSymetricalForOpponents": false
            },
            {
              "direction": "column",
              "style": {"width": "12vh"},
              "content": [
                {
                  "section": "C1R1",
                  "style": false
                },
                {
                  "section": "C1R2",
                  "style": false
                },
                {
                  "section": "C1R3",
                  "style": false
                }
              ],
              "isSymetricalForOpponents": false
            },
            {
              "direction": "column",
              "style": {"width": "12vh"},
              "content": [
                {
                  "section": "C2R1",
                  "style": false
                },
                {
                  "section": "C2R2",
                  "style": false
                },
                {
                  "section": "C2R3",
                  "style": false
                }
              ],
              "isSymetricalForOpponents": false
            },
            {
              "direction": "column",
              "style": {"width": "12vh"},
              "content": [
                {
                  "section": "C3R1",
                  "style": false
                },
                {
                  "section": "C3R2",
                  "style": false
                },
                {
                  "section": "C3R3",
                  "style": false
                }
              ],
              "isSymetricalForOpponents": false
            },
            {
              "direction": "column",
              "style": {"width": "12vh"},
              "content": [
                {
                  "section": "C4R1",
                  "style": false
                },
                {
                  "section": "C4R2",
                  "style": false
                },
                {
                  "section": "C4R3",
                  "style": false
                }
              ],
              "isSymetricalForOpponents": false
            }
          ]
        },
        "categoriesAlreadyOnBoard": [
          "Fodder",
          "Monarch",
          "C1R1",
          "C1R2",
          "C1R3",
          "C2R1",
          "C2R2",
          "C2R3",
          "C3R1",
          "C3R2",
          "C3R3",
          "C4R1",
          "C4R2",
          "C4R3"
        ],
        "autoPlayFromHand": {},
        "autoPlayFromStack": {},
        "sectionsDict": {
          "Monarch": {
            "title": "Monarch",
            "isHidden": "no",
            "height": "MEDIUM",
            "alignment": "DECK",
            "opponentAlignment": false,
            "noAutoPayTo": "true",
            "isHorizontalAllowed": false,
            "displayedTitle": "",
            "enterTapped": false,
            "enterSpun": false,
            "isGroupForbidden": false,
            "keepTappedNewTurn": false,
            "showHiddenCardInHistory": false,
            "noQuickActions": true
          },
          "Fodder": {
            "title": "Fodder",
            "isHidden": "yes",
            "height": "MEDIUM",
            "alignment": "DECK",
            "opponentAlignment": false,
            "noAutoPayTo": true,
            "isHorizontalAllowed": false,
            "displayedTitle": "",
            "noQuickActions": false,
            "enterTapped": false,
            "enterSpun": false,
            "isGroupForbidden": false,
            "keepTappedNewTurn": false,
            "showHiddenCardInHistory": false
          },
          "C1R1": {
            "title": "C1R1",
            "isHidden": "no",
            "height": "SMALL",
            "alignment": "CENTER",
            "opponentAlignment": false,
            "noAutoPayTo": true,
            "isHorizontalAllowed": true,
            "displayedTitle": "Front",
            "noQuickActions": false,
            "enterTapped": false,
            "enterSpun": false,
            "isGroupForbidden": false,
            "keepTappedNewTurn": false,
            "showHiddenCardInHistory": false
          },
          "C1R2": {
            "title": "C1R2",
            "isHidden": "no",
            "height": "SMALL",
            "alignment": "CENTER",
            "opponentAlignment": false,
            "noAutoPayTo": true,
            "isHorizontalAllowed": true,
            "displayedTitle": "Back",
            "noQuickActions": false,
            "enterTapped": false,
            "enterSpun": false,
            "isGroupForbidden": false,
            "keepTappedNewTurn": false,
            "showHiddenCardInHistory": false
          },
          "C1R3": {
            "title": "C1R3",
            "isHidden": "no",
            "height": "SMALL",
            "alignment": "CENTER",
            "opponentAlignment": false,
            "noAutoPayTo": true,
            "isHorizontalAllowed": true,
            "displayedTitle": "A/C",
            "noQuickActions": false,
            "enterTapped": false,
            "enterSpun": false,
            "isGroupForbidden": false,
            "keepTappedNewTurn": false,
            "showHiddenCardInHistory": false
          },
          "C2R1": {
            "title": "C2R1",
            "isHidden": "no",
            "height": "SMALL",
            "alignment": "CENTER",
            "opponentAlignment": false,
            "noAutoPayTo": true,
            "isHorizontalAllowed": true,
            "displayedTitle": "Front",
            "noQuickActions": false,
            "enterTapped": false,
            "enterSpun": false,
            "isGroupForbidden": false,
            "keepTappedNewTurn": false,
            "showHiddenCardInHistory": false
          },
          "C2R2": {
            "title": "C2R2",
            "isHidden": "no",
            "height": "SMALL",
            "alignment": "CENTER",
            "opponentAlignment": false,
            "noAutoPayTo": true,
            "isHorizontalAllowed": true,
            "displayedTitle": "Back",
            "noQuickActions": false,
            "enterTapped": false,
            "enterSpun": false,
            "isGroupForbidden": false,
            "keepTappedNewTurn": false,
            "showHiddenCardInHistory": false
          },
          "C2R3": {
            "title": "C2R3",
            "isHidden": "no",
            "height": "SMALL",
            "alignment": "CENTER",
            "opponentAlignment": false,
            "noAutoPayTo": true,
            "isHorizontalAllowed": true,
            "displayedTitle": "A/C",
            "noQuickActions": false,
            "enterTapped": false,
            "enterSpun": false,
            "isGroupForbidden": false,
            "keepTappedNewTurn": false,
            "showHiddenCardInHistory": false
          },
          "C3R1": {
            "title": "C3R1",
            "isHidden": "no",
            "height": "SMALL",
            "alignment": "CENTER",
            "opponentAlignment": false,
            "noAutoPayTo": true,
            "isHorizontalAllowed": true,
            "displayedTitle": "Front",
            "noQuickActions": false,
            "enterTapped": false,
            "enterSpun": false,
            "isGroupForbidden": false,
            "keepTappedNewTurn": false,
            "showHiddenCardInHistory": false
          },
          "C3R2": {
            "title": "C3R2",
            "isHidden": "no",
            "height": "SMALL",
            "alignment": "CENTER",
            "opponentAlignment": false,
            "noAutoPayTo": true,
            "isHorizontalAllowed": true,
            "displayedTitle": "Back",
            "noQuickActions": false,
            "enterTapped": false,
            "enterSpun": false,
            "isGroupForbidden": false,
            "keepTappedNewTurn": false,
            "showHiddenCardInHistory": false
          },
          "C3R3": {
            "title": "C3R3",
            "isHidden": "no",
            "height": "SMALL",
            "alignment": "CENTER",
            "opponentAlignment": false,
            "noAutoPayTo": true,
            "isHorizontalAllowed": true,
            "displayedTitle": "A/C",
            "noQuickActions": false,
            "enterTapped": false,
            "enterSpun": false,
            "isGroupForbidden": false,
            "keepTappedNewTurn": false,
            "showHiddenCardInHistory": false
          },
          "C4R1": {
            "title": "C4R1",
            "isHidden": "no",
            "height": "SMALL",
            "alignment": "CENTER",
            "opponentAlignment": false,
            "noAutoPayTo": true,
            "isHorizontalAllowed": true,
            "displayedTitle": "Front",
            "noQuickActions": false,
            "enterTapped": false,
            "enterSpun": false,
            "isGroupForbidden": false,
            "keepTappedNewTurn": false,
            "showHiddenCardInHistory": false
          },
          "C4R2": {
            "title": "C4R2",
            "isHidden": "no",
            "height": "SMALL",
            "alignment": "CENTER",
            "opponentAlignment": false,
            "noAutoPayTo": true,
            "isHorizontalAllowed": true,
            "displayedTitle": "Back",
            "noQuickActions": false,
            "enterTapped": false,
            "enterSpun": false,
            "isGroupForbidden": false,
            "keepTappedNewTurn": false,
            "showHiddenCardInHistory": false
          },
          "C4R3": {
            "title": "C4R3",
            "isHidden": "no",
            "height": "SMALL",
            "alignment": "CENTER",
            "opponentAlignment": false,
            "noAutoPayTo": true,
            "isHorizontalAllowed": true,
            "displayedTitle": "A/C",
            "noQuickActions": false,
            "enterTapped": false,
            "enterSpun": false,
            "isGroupForbidden": false,
            "keepTappedNewTurn": false,
            "showHiddenCardInHistory": false
          }
        }
      }
    }
  }
}